MANIFEST.in
README.md
setup.cfg
setup.py
bin/stellar_keygen.py
bin/stellar_send.py
stellar/__init__.py
stellar/address.py
stellar/base58.py
stellar/connection_manager.py
stellar/crypto.py
stellar/ledger.py
stellar/serialize.py
stellar/transaction.py
stellar/utils.py
stellar/version.py
stellar_py.egg-info/PKG-INFO
stellar_py.egg-info/SOURCES.txt
stellar_py.egg-info/dependency_links.txt
stellar_py.egg-info/requires.txt
stellar_py.egg-info/top_level.txt