Metadata-Version: 1.1
Name: stellar-py
Version: 0.1.1
Summary: Python client library for Stellar
Home-page: https://github.com/johansten/stellar-py
Author: Johan Stén
Author-email: johan.sten@gmail.com
License: LICENSE.txt
Platform: UNKNOWN
Classifier: Programming Language :: Python
Classifier: Development Status :: 2 - Pre-Alpha
Classifier: Intended Audience :: Developers
Classifier: License :: OSI Approved :: BSD License
Classifier: Operating System :: OS Independent
Classifier: Topic :: Software Development :: Libraries :: Python Modules
